odoo10_addon_sale_product_set_layout-10.0.1.0.1-py3.8-nspkg.pth
odoo/addons/sale_product_set_layout/README.rst
odoo/addons/sale_product_set_layout/__init__.py
odoo/addons/sale_product_set_layout/__manifest__.py
odoo/addons/sale_product_set_layout/demo/product_set.xml
odoo/addons/sale_product_set_layout/i18n/ca.po
odoo/addons/sale_product_set_layout/i18n/es.po
odoo/addons/sale_product_set_layout/i18n/fr.po
odoo/addons/sale_product_set_layout/i18n/hr.po
odoo/addons/sale_product_set_layout/i18n/pt.po
odoo/addons/sale_product_set_layout/i18n/sale_product_set_layout.pot
odoo/addons/sale_product_set_layout/i18n/sl.po
odoo/addons/sale_product_set_layout/models/__init__.py
odoo/addons/sale_product_set_layout/models/product_set.py
odoo/addons/sale_product_set_layout/security/groups.xml
odoo/addons/sale_product_set_layout/static/description/icon.png
odoo/addons/sale_product_set_layout/static/description/icon.svg
odoo/addons/sale_product_set_layout/tests/__init__.py
odoo/addons/sale_product_set_layout/tests/test_product_set_layout.py
odoo/addons/sale_product_set_layout/views/product_set.xml
odoo/addons/sale_product_set_layout/wizard/__init__.py
odoo/addons/sale_product_set_layout/wizard/product_set_add.py
odoo10_addon_sale_product_set_layout-10.0.1.0.1.dist-info/METADATA
odoo10_addon_sale_product_set_layout-10.0.1.0.1.dist-info/WHEEL
odoo10_addon_sale_product_set_layout-10.0.1.0.1.dist-info/namespace_packages.txt
odoo10_addon_sale_product_set_layout-10.0.1.0.1.dist-info/top_level.txt
odoo10_addon_sale_product_set_layout-10.0.1.0.1.dist-info/RECORD
